donetick_mcp/__init__.py
donetick_mcp/client.py
donetick_mcp/config.py
donetick_mcp/models.py
donetick_mcp/server.py
donetick_mcp_server-0.3.13.dist-info/licenses/LICENSE
donetick_mcp_server-0.3.13.dist-info/METADATA
donetick_mcp_server-0.3.13.dist-info/WHEEL
donetick_mcp_server-0.3.13.dist-info/entry_points.txt
donetick_mcp_server-0.3.13.dist-info/top_level.txt
donetick_mcp_server-0.3.13.dist-info/RECORD
