Metadata-Version: 2.4
Name: donetick-mcp-server
Version: 0.3.13
Summary: MCP server for Donetick chores management with JWT authentication, Full API support, and 20 MCP tools
Author-email: Jason <jason1365@users.noreply.github.com>
License: MIT
Project-URL: Homepage, https://github.com/jason1365/donetick-mcp-server
Project-URL: Documentation, https://github.com/jason1365/donetick-mcp-server#readme
Project-URL: Repository, https://github.com/jason1365/donetick-mcp-server
Project-URL: Issues, https://github.com/jason1365/donetick-mcp-server/issues
Project-URL: Changelog, https://github.com/jason1365/donetick-mcp-server/releases
Keywords: mcp,donetick,chores,api,claude
Classifier: Development Status :: 4 - Beta
Classifier: Intended Audience :: Developers
Classifier: License :: OSI Approved :: MIT License
Classifier: Programming Language :: Python :: 3
Classifier: Programming Language :: Python :: 3.11
Classifier: Programming Language :: Python :: 3.12
Classifier: Programming Language :: Python :: 3.13
Requires-Python: >=3.11
License-File: LICENSE
Requires-Dist: mcp>=1.20.0
Requires-Dist: httpx>=0.27.0
Requires-Dist: pydantic>=2.0.0
Requires-Dist: python-dotenv>=1.0.0
Requires-Dist: pytz>=2024.1
Provides-Extra: dev
Requires-Dist: pytest>=8.0.0; extra == "dev"
Requires-Dist: pytest-asyncio>=0.23.0; extra == "dev"
Requires-Dist: pytest-mock>=3.12.0; extra == "dev"
Requires-Dist: pytest-httpx>=0.30.0; extra == "dev"
Dynamic: license-file
